{
  "request_id": "TUR-foreign_policy-sources-1780797238210",
  "country_code": "TUR",
  "module": "foreign_policy",
  "needed_for_questions": [
    "For foreign policy, what source-backed evidence answers dossier question 1?",
    "For foreign policy, what source-backed evidence answers dossier question 2?",
    "For foreign policy, what source-backed evidence answers dossier question 3?",
    "For foreign policy, what source-backed evidence answers dossier question 4?",
    "For foreign policy, what source-backed evidence answers dossier question 5?",
    "For foreign policy, what source-backed evidence answers dossier question 6?",
    "For foreign policy, what source-backed evidence answers dossier question 7?",
    "For foreign policy, what source-backed evidence answers dossier question 8?",
    "For foreign policy, what source-backed evidence answers dossier question 9?",
    "For foreign policy, what source-backed evidence answers dossier question 10?",
    "For foreign policy, what source-backed evidence answers dossier question 11?",
    "For foreign policy, what source-backed evidence answers dossier question 12?",
    "For foreign policy, what source-backed evidence answers dossier question 13?",
    "For foreign policy, what source-backed evidence answers dossier question 14?",
    "For foreign policy, what source-backed evidence answers dossier question 15?",
    "For foreign policy, what source-backed evidence answers dossier question 16?",
    "For foreign policy, what source-backed evidence answers dossier question 17?",
    "For foreign policy, what source-backed evidence answers dossier question 18?",
    "For foreign policy, what source-backed evidence answers dossier question 19?",
    "For foreign policy, what source-backed evidence answers dossier question 20?",
    "For foreign policy, what source-backed evidence answers dossier question 21?",
    "For foreign policy, what source-backed evidence answers dossier question 22?",
    "For foreign policy, what source-backed evidence answers dossier question 23?",
    "For foreign policy, what source-backed evidence answers dossier question 24?",
    "For foreign policy, what source-backed evidence answers dossier question 25?"
  ],
  "suggested_source_types": [
    "official government biography",
    "parliament profile",
    "major news profile",
    "book/chapter",
    "think tank report"
  ],
  "priority": "high",
  "status": "open",
  "notes": ""
}
